refactorguide/__init__.py
refactorguide/__main__.py
refactorguide/cli.py
refactorguide/desgin.py
refactorguide/design_parser.py
refactorguide/filters.py
refactorguide/formatters.py
refactorguide/input_idea.py
refactorguide/models.py
refactorguide/output_md.py
refactorguide/output_uml.py
refactorguide/smells.py
refactorguide/statistics.py
refactorguide/tools.py
refactorguide-0.1.3.dist-info/AUTHORS.rst
refactorguide-0.1.3.dist-info/LICENSE
refactorguide-0.1.3.dist-info/METADATA
refactorguide-0.1.3.dist-info/WHEEL
refactorguide-0.1.3.dist-info/entry_points.txt
refactorguide-0.1.3.dist-info/top_level.txt
refactorguide-0.1.3.dist-info/RECORD
