Metadata-Version: 2.1
Name: refactorguide
Version: 0.1.3
Summary: Generate guides for refactor.
Home-page: https://github.com/qinyu/refactorguide
Author: Qin Yu
Author-email: qinyusuain@gmail.com
License: MIT license
Keywords: refactorguide
Platform: UNKNOWN
Classifier: Development Status :: 2 - Pre-Alpha
Classifier: Intended Audience :: Developers
Classifier: License :: OSI Approved :: MIT License
Classifier: Natural Language :: English
Classifier: Programming Language :: Python :: 3
Classifier: Programming Language :: Python :: 3.6
Classifier: Programming Language :: Python :: 3.7
Classifier: Programming Language :: Python :: 3.8
Requires-Python: >=3.6
